mxq_data_science_db/db/__init__.py
mxq_data_science_db/db/db.py
mxq_data_science_db/db/models/base.py
mxq_data_science_db/db/models/db_comex.py
mxq_data_science_db/db/models/db_commodity.py
mxq_data_science_db/db/models/db_economia.py
mxq_data_science_db/settings/__init__.py
mxq_data_science_db/settings/logger.py
mxq_data_science_db/settings/settings.py
mxq_data_science_db/utils/__init__.py
mxq_data_science_db/utils/data_lake.py
mxq_data_science_db/utils/dropbox.py
mxq_data_science_db/utils/teams_alert.py
mxq_data_science_db/utils/utils.py
mxq_data_science_db-1.2.18.dist-info/METADATA
mxq_data_science_db-1.2.18.dist-info/WHEEL
mxq_data_science_db-1.2.18.dist-info/RECORD
